[
  {
    "id": "1003d375-775a-4e60-b11b-2e68a9e16c81",
    "title": "Building a concurrency library on top of Loom",
    "url": "https://www.umatr.io/scala-matters",
    "when": "2023-11-01T00:00:00Z",
    "tags": [
      "scala",
      "loom",
      "concurrency",
      "structural concurrency",
      "effects",
      "java",
      "ox"
    ],
    "where": "Paris, France",
    "conference": "Scala Matters",
    "video": "e0b300b8-4c3b-4556-8291-cd60991d0bde"
  },
  {
    "id": "32379977-ba5c-4d75-84f7-8f30a2ce7743",
    "title": "Building a concurrency library on top of Loom",
    "url": "https://nescalas.github.io",
    "when": "2023-10-01T00:00:00Z",
    "tags": [
      "scala",
      "loom",
      "concurrency",
      "structural concurrency",
      "effects",
      "java",
      "ox"
    ],
    "where": "Online",
    "conference": "NEScala"
  },
  {
    "id": "d2495234-2025-42a2-b2f8-8808f1c3b9a2",
    "title": "Building a concurrency library on top of Loom",
    "url": "https://www.devtalks.ro",
    "when": "2023-09-01T00:00:00Z",
    "tags": [
      "scala",
      "loom",
      "concurrency",
      "structural concurrency",
      "effects",
      "java",
      "ox"
    ],
    "where": "Cluj-Napoca, Romania",
    "conference": "DevTalks"
  },
  {
    "id": "01d5c0b0-57cf-45ac-83d6-f53f8b973f7e",
    "title": "Concurrency in Scala and on the JVM",
    "url": "https://scaladays.org",
    "when": "2023-09-01T00:00:00Z",
    "tags": [
      "scala",
      "java",
      "unison",
      "concurrency",
      "zio",
      "cats-effect",
      "effects",
      "loom",
      "ox"
    ],
    "where": "Madrid, Spain",
    "conference": "ScalaDays",
    "slides": "http://www.warski.org/blog/wp-content/uploads/2023/09/concurrency-in-scala-and-on-the-jvm.pdf",
    "video": "e285c8bb-5a23-40f3-a4d9-4626f1df9a37"
  },
  {
    "id": "e81cd2f2-022f-4e5f-b085-0276afe6973f",
    "title": "Unison: program differently",
    "url": "https://www.lambdadays.org/lambdadays2023",
    "when": "2023-06-01T00:00:00Z",
    "tags": [
      "unison",
      "functional programming",
      "effects"
    ],
    "where": "Kraków, Poland",
    "conference": "LambdaDays",
    "video": "b657fa3b-b569-4df2-8b11-723bc0d55294"
  },
  {
    "id": "1001dd01-47c3-4142-be9e-121ef8a98ac4",
    "title": "Building a concurrency library on top of Loom",
    "url": "https://devoxx.pl",
    "when": "2023-05-01T00:00:00Z",
    "tags": [
      "scala",
      "loom",
      "concurrency",
      "structural concurrency",
      "effects",
      "java",
      "ox"
    ],
    "where": "Kraków, Poland",
    "conference": "Devoxx Poland",
    "video": "f4f8247b-1484-4f35-aa47-102a752b59be"
  },
  {
    "id": "6a8c832d-584b-4d1f-b466-532b585e5a79",
    "title": "Essence of an HTTP framework",
    "url": "https://devdays.lt",
    "when": "2023-05-01T00:00:00Z",
    "tags": [
      "scala",
      "tapir",
      "http",
      "framework",
      "functional pogramming",
      "openapi"
    ],
    "where": "Vilnius, Lithuania",
    "conference": "DevDays"
  },
  {
    "id": "74fcf42c-37f2-487a-a463-cc5eaa795e7b",
    "title": "Effects: To Be Or Not To Be?",
    "url": "https://www.jug.ch",
    "when": "2023-05-01T00:00:00Z",
    "tags": [
      "effects",
      "scala",
      "java",
      "unison",
      "functional programming",
      "zio",
      "cats-effect",
      "loom"
    ],
    "where": "Zurich, Switzerland",
    "conference": "Jug Switzerland",
    "slides": "http://www.warski.org/blog/wp-content/uploads/2023/08/Effects-to-be-or-not-to-be.pdf"
  },
  {
    "id": "ad26f1ec-12e6-45d6-aa86-050eb06f5737",
    "title": "Effects: To Be Or Not To Be?",
    "url": "https://geecon.org",
    "when": "2023-04-01T00:00:00Z",
    "tags": [
      "effects",
      "scala",
      "java",
      "unison",
      "functional programming",
      "zio",
      "cats-effect",
      "loom"
    ],
    "where": "Kraków, Poland",
    "conference": "GeeCON",
    "video": "6b6af030-be8e-4df7-8ac4-f496743fa1b4"
  },
  {
    "id": "eb541fc9-11b7-41e6-9c11-f5fd18e6cef3",
    "title": "Direct style Scala – panel dyskusyjny",
    "url": "https://www.meetup.com/pl-PL/krakow-scala-user-group/",
    "when": "2023-04-01T00:00:00Z",
    "tags": [
      "scala",
      "ox",
      "functional programming",
      "effects"
    ],
    "where": "Kraków, Poland",
    "conference": "KSUG"
  },
  {
    "id": "58630ec0-bba3-43c8-8790-480d4f5db785",
    "title": "Oxes, Tapirs and Sttps",
    "url": "https://www.scalar-conf.com",
    "when": "2023-04-01T00:00:00Z",
    "tags": [
      "scala",
      "ox",
      "effects",
      "loom",
      "tapir",
      "http"
    ],
    "where": "Warszawa, Poland",
    "conference": "Scalar",
    "video": "50aa35e1-041f-46cd-93aa-52b9636ff5b2"
  },
  {
    "id": "fe7537a6-8d78-484b-b80d-ccd7f4984dd6",
    "title": "Effects: To Be Or Not To Be?",
    "url": "https://www.functionalscala.com",
    "when": "2022-12-01T00:00:00Z",
    "tags": [
      "effects",
      "scala",
      "java",
      "unison",
      "functional programming",
      "zio",
      "cats-effect",
      "loom"
    ],
    "where": "London, UK",
    "conference": "Functional Scala",
    "video": "f8d55a13-e3d3-4336-bb2e-1c17bc681d7e"
  },
  {
    "id": "8f6f5a0f-ca3d-4ff9-a633-128c4c7e66b9",
    "title": "Never say never",
    "url": "https://sphere.it/event-series/buginnings-in-it/",
    "when": "2022-11-01T00:00:00Z",
    "tags": [
      "softwaremill",
      "personal"
    ],
    "where": "Kraków, Poland",
    "conference": "BUGinnings",
    "video": "5fbdfc93-65df-4d80-a2d6-4f17ea85e5a1"
  },
  {
    "id": "54bcd6a5-2d7c-4d7e-81db-3d8bf010cea6",
    "title": "Delivering: from Kafka to web sockets",
    "when": "2022-11-01T00:00:00Z",
    "tags": [
      "kafka",
      "web sockets",
      "streaming"
    ],
    "where": "Warsaw, Poland",
    "conference": "Confluent Lunch and Learn",
    "slides": "http://www.warski.org/blog/wp-content/uploads/2023/08/Delivering-from-Kafka-to-WebSockets.pdf"
  },
  {
    "id": "67d85764-5b48-41e5-8098-57f0b8070f10",
    "title": "Adam Warski on Scala and Tapir",
    "url": "https://se-radio.net/2022/11/episode-537-adam-warski-on-scala-and-tapir/",
    "when": "2022-10-01T00:00:00Z",
    "tags": [
      "scala",
      "tapir"
    ],
    "where": "Online",
    "conference": "SE Radio",
    "audio": "https://www.se-radio.net/2022/11/episode-537-adam-warski-on-scala-and-tapir/"
  },
  {
    "id": "99b76c15-e30e-4167-a45d-e7dc8c304315",
    "title": "Delivering: from Kafka to web sockets",
    "url": "https://bolt.eu/en/blog/event-recap-warsaw-tech-exchange/",
    "when": "2022-04-01T00:00:00Z",
    "tags": [
      "kafka",
      "web sockets",
      "streaming"
    ],
    "where": "Warsaw, Poland",
    "conference": "Bolt Warsaw Tech Exchange"
  },
  {
    "id": "8bcb636c-f94a-4e95-a6ab-6a54156f1184",
    "title": "Exposing an HTTP API using Scala3 (workshop)",
    "url": "https://www.scale.bythebay.io",
    "when": "2021-10-01T00:00:00Z",
    "tags": [
      "scala",
      "tapir"
    ],
    "where": "Online",
    "conference": "Scale By The Bay"
  },
  {
    "id": "39824e9f-fe75-491a-a5a5-bdf1a73d0c8d",
    "title": "Scala 3 Metaprogramming by Example",
    "url": "https://devdays.lt",
    "when": "2021-06-01T00:00:00Z",
    "tags": [
      "scala",
      "macros",
      "metaprogramming"
    ],
    "where": "Online",
    "conference": "DevDaysEurope",
    "video": "bd1220f3-303d-4934-8180-4594665958e0"
  },
  {
    "id": "b6558141-23f6-4448-bbb0-827e059780c2",
    "title": "Functional WebSockets",
    "url": "http://www.scalacon.org",
    "when": "2021-05-01T00:00:00Z",
    "tags": [
      "scala",
      "tapir",
      "web sockets"
    ],
    "where": "Online",
    "conference": "ScalaCon",
    "video": "6bffdd8a-2dd8-45d8-87d3-b707976cc0e1"
  },
  {
    "id": "fc83d594-2a79-4fb4-b0d0-456ad511cde8",
    "title": "Delivering: from Kafka to WebSockets",
    "url": "https://www.kafka-summit.org",
    "when": "2021-05-01T00:00:00Z",
    "tags": [
      "kafka",
      "web sockets",
      "streaming"
    ],
    "where": "Online",
    "conference": "Kafka Summit Europe",
    "video": "0464a863-d459-4771-91ee-e5661ef4f96a"
  },
  {
    "id": "5fb1b007-b4cf-4a72-9eea-b215d8c4bb4e",
    "title": "Your HTTP endpoints are data, as well!",
    "url": "https://www.jfokus.se/articles/brownbag21",
    "when": "2021-03-01T00:00:00Z",
    "tags": [
      "scala",
      "tapir",
      "functional programming"
    ],
    "where": "Online",
    "conference": "JFokus Brown Bag lunch",
    "video": "313c99c4-d1ff-4f9c-a84f-3b45192fdd84"
  },
  {
    "id": "333761b8-a84e-4ceb-a944-49e27bbc45ce",
    "title": "Context is King",
    "url": "https://www.youtube.com/c/ScalaintheCity/videos",
    "when": "2021-03-01T00:00:00Z",
    "tags": [
      "scala",
      "functional programming",
      "scala3"
    ],
    "where": "Online",
    "conference": "Scala in the City",
    "video": "d3472706-ec27-4f9d-9027-44e16f58302a"
  },
  {
    "id": "035ba7fd-bbfa-4ffe-83fd-4627b734b613",
    "title": "Delivering: from Kafka to WebSockets",
    "url": "https://www.google.com/url?sa=t&source=web&rct=j&opi=89978449&url=https://events.geekle.us/wsas/&ved=2ahUKEwjAzoa50NGFAxUbGRAIHZ0MBnsQFnoECBUQAQ&usg=AOvVaw1hCNb7F9-g4m3ersfh1o5O",
    "when": "2021-01-01T00:00:00Z",
    "tags": [
      "kafka",
      "web sockets",
      "streaming"
    ],
    "where": "Online",
    "conference": "Geekle Worldwide Software Architecture Summit"
  },
  {
    "id": "dfca19aa-304c-4942-b483-325823964953",
    "title": "Your HTTP endpoints are data, as well!",
    "when": "2020-12-01T00:00:00Z",
    "tags": [
      "scala",
      "tapir",
      "functional programming"
    ],
    "where": "Online",
    "conference": "JLove",
    "video": "666e6189-a268-4038-b0a4-2bb52062a089"
  },
  {
    "id": "3b81644c-3428-48c3-8224-310fa65b31f8",
    "title": "Metaprogramming in Scala 3 by example",
    "url": "https://www.functionalscala.com",
    "when": "2020-12-01T00:00:00Z",
    "tags": [
      "scala",
      "scala3",
      "macros",
      "metaprogramming"
    ],
    "where": "Online",
    "conference": "FunctionalScala",
    "video": "b39905a1-bd3a-4d71-bf55-6991cdb00967"
  },
  {
    "id": "634926ac-eb4f-46d3-9024-7b511354575b",
    "title": "Project Loom? Better Futures? What’s next for JVM concurrent programming",
    "url": "https://www.scale.bythebay.io",
    "when": "2020-11-01T00:00:00Z",
    "tags": [
      "loom",
      "virtual threads",
      "java21",
      "concurrency",
      "jvm",
      "scala",
      "functional programming"
    ],
    "where": "Online",
    "conference": "ScaleByTheBay",
    "video": "1295a3f2-a404-4597-8bed-70edbf31914a"
  },
  {
    "id": "19375228-373b-4dbd-b00d-012696b67f0e",
    "title": "Definicja API HTTP: to też dane",
    "url": "https://tech.3camp.pl",
    "when": "2020-10-01T00:00:00Z",
    "tags": [
      "scala",
      "tapir",
      "functional programming"
    ],
    "where": "Online",
    "conference": "TECH3Camp"
  },
  {
    "id": "ddcc7aa1-9036-4de8-b841-1f0a13558ac7",
    "title": "JVM Wars",
    "when": "2020-10-01T00:00:00Z",
    "tags": [
      "scala",
      "kotlin",
      "java"
    ],
    "where": "Online",
    "conference": "JVM Wars 2020",
    "video": "1ac101b7-673b-42d1-ab99-1f920bc237e5"
  },
  {
    "id": "57c49f1f-2a5e-40c3-b187-f9c85c1321d5",
    "title": "Functional Scala CRUD",
    "url": "https://www.lambdaconf.us",
    "when": "2020-10-01T00:00:00Z",
    "tags": [
      "scala",
      "functional programming"
    ],
    "where": "Online",
    "conference": "LambdaConf"
  },
  {
    "id": "e03112fe-9cdb-4f22-8974-3105339ca9fe",
    "title": "Scala 3 panel",
    "when": "2020-09-01T00:00:00Z",
    "tags": [
      "scala",
      "scala3"
    ],
    "where": "Online",
    "conference": "FP in the City",
    "video": "4ff1a392-ab8e-4aed-ab62-6555bcaea3b0"
  },
  {
    "id": "b5ead662-f2e2-40dd-98fd-88676723c50a",
    "title": "Projekt Loom, a może lepszy Future?",
    "url": "https://www.meetup.com/pl-PL/wroclawjug/",
    "when": "2020-09-01T00:00:00Z",
    "tags": [
      "loom",
      "java21",
      "virtual threads",
      "reactive programming",
      "concurrency"
    ],
    "where": "Online",
    "conference": "WroJUG"
  },
  {
    "id": "bdff4f41-81e6-4e98-b674-8ff31d28ffba",
    "title": "Project Loom? Better Futures? What’s next for JVM concurrent programming",
    "url": "https://geekle.us",
    "when": "2020-08-01T00:00:00Z",
    "tags": [
      "loom",
      "java21",
      "virtual threads",
      "concurrency",
      "scala",
      "reactive programming"
    ],
    "where": "Online",
    "conference": "Geekle Java Summit",
    "video": "798c8da2-5d4d-478f-800d-8c03ea137044"
  },
  {
    "id": "869c17e8-6221-45f7-ad7a-6c774b855398",
    "title": "Happy eyeballs live-coding using ZIO",
    "url": "https://www.youtube.com/c/ScalaintheCity/videos",
    "when": "2020-07-01T00:00:00Z",
    "tags": [
      "scala",
      "zio",
      "functional programming"
    ],
    "where": "Online",
    "conference": "Scala in the City",
    "video": "5a47c78a-974e-4e85-8096-7a5e87966024"
  },
  {
    "id": "827a904d-42e8-4b99-b2b3-0d37939e4d75",
    "title": "FP + relational databases = ?",
    "when": "2020-05-01T00:00:00Z",
    "tags": [
      "functional programming",
      "scala"
    ],
    "where": "Online",
    "conference": "London Scala Talks"
  }
]